tacpho/adapters/_version.py
tacpho/adapters/mm.py
tacpho.adapters-0.3.0.data/scripts/mm.py
tacpho.adapters-0.3.0.dist-info/LICENSE
tacpho.adapters-0.3.0.dist-info/METADATA
tacpho.adapters-0.3.0.dist-info/WHEEL
tacpho.adapters-0.3.0.dist-info/top_level.txt
tacpho.adapters-0.3.0.dist-info/RECORD
